[{"index":0,"identificacion":1,"barrio":"San Benito"},{"index":1,"identificacion":2,"barrio":"Guayaquil"},{"index":2,"identificacion":3,"barrio":"Buenos Aires"},{"index":3,"identificacion":4,"barrio":"San Benito"},{"index":4,"identificacion":5,"barrio":"Buenos Aires"},{"index":5,"identificacion":6,"barrio":"Prado"},{"index":6,"identificacion":7,"barrio":"Laureles"},{"index":7,"identificacion":8,"barrio":"Manrique"},{"index":8,"identificacion":9,"barrio":"Laureles"},{"index":9,"identificacion":10,"barrio":"San Benito"},{"index":10,"identificacion":11,"barrio":"Buenos Aires"},{"index":11,"identificacion":12,"barrio":"Buenos Aires"},{"index":12,"identificacion":13,"barrio":"Guayaquil"},{"index":13,"identificacion":14,"barrio":"Buenos Aires"},{"index":14,"identificacion":15,"barrio":"Guayaquil"},{"index":15,"identificacion":16,"barrio":"Prado"},{"index":16,"identificacion":17,"barrio":"Manrique"},{"index":17,"identificacion":18,"barrio":"San Benito"},{"index":18,"identificacion":19,"barrio":"Guayaquil"},{"index":19,"identificacion":20,"barrio":"Manrique"},{"index":20,"identificacion":21,"barrio":"Buenos Aires"},{"index":21,"identificacion":22,"barrio":"Buenos Aires"},{"index":22,"identificacion":23,"barrio":"Manrique"},{"index":23,"identificacion":24,"barrio":"Buenos Aires"},{"index":24,"identificacion":25,"barrio":"Prado"},{"index":25,"identificacion":26,"barrio":"Prado"},{"index":26,"identificacion":27,"barrio":"Manrique"},{"index":27,"identificacion":28,"barrio":"Guayaquil"},{"index":28,"identificacion":29,"barrio":"Guayaquil"},{"index":29,"identificacion":30,"barrio":"Manrique"},{"index":30,"identificacion":31,"barrio":"Guayaquil"},{"index":31,"identificacion":32,"barrio":"Guayaquil"},{"index":32,"identificacion":33,"barrio":"Prado"},{"index":33,"identificacion":34,"barrio":"Guayaquil"},{"index":34,"identificacion":35,"barrio":"Laureles"},{"index":35,"identificacion":36,"barrio":"San Benito"},{"index":36,"identificacion":37,"barrio":"Buenos Aires"},{"index":37,"identificacion":38,"barrio":"Laureles"},{"index":38,"identificacion":39,"barrio":"Guayaquil"},{"index":39,"identificacion":40,"barrio":"Prado"},{"index":40,"identificacion":41,"barrio":"Manrique"},{"index":41,"identificacion":42,"barrio":"Guayaquil"},{"index":42,"identificacion":43,"barrio":"Prado"},{"index":43,"identificacion":44,"barrio":"San Benito"},{"index":44,"identificacion":45,"barrio":"Guayaquil"},{"index":45,"identificacion":46,"barrio":"Manrique"},{"index":46,"identificacion":47,"barrio":"Prado"},{"index":47,"identificacion":48,"barrio":"Prado"},{"index":48,"identificacion":49,"barrio":"Prado"},{"index":49,"identificacion":50,"barrio":"San Benito"},{"index":50,"identificacion":51,"barrio":"Guayaquil"},{"index":51,"identificacion":52,"barrio":"San Benito"},{"index":52,"identificacion":53,"barrio":"Buenos Aires"},{"index":53,"identificacion":54,"barrio":"Buenos Aires"},{"index":54,"identificacion":55,"barrio":"Guayaquil"},{"index":55,"identificacion":56,"barrio":"San Benito"},{"index":56,"identificacion":57,"barrio":"Manrique"},{"index":57,"identificacion":58,"barrio":"Prado"},{"index":58,"identificacion":59,"barrio":"Prado"},{"index":59,"identificacion":60,"barrio":"Guayaquil"},{"index":60,"identificacion":61,"barrio":"Buenos Aires"},{"index":61,"identificacion":62,"barrio":"Buenos Aires"},{"index":62,"identificacion":63,"barrio":"Prado"},{"index":63,"identificacion":64,"barrio":"Guayaquil"},{"index":64,"identificacion":65,"barrio":"San Benito"},{"index":65,"identificacion":66,"barrio":"Buenos Aires"},{"index":66,"identificacion":67,"barrio":"San Benito"},{"index":67,"identificacion":68,"barrio":"Buenos Aires"},{"index":68,"identificacion":69,"barrio":"Buenos Aires"},{"index":69,"identificacion":70,"barrio":"Laureles"},{"index":70,"identificacion":71,"barrio":"Buenos Aires"},{"index":71,"identificacion":72,"barrio":"Manrique"},{"index":72,"identificacion":73,"barrio":"Guayaquil"},{"index":73,"identificacion":74,"barrio":"Guayaquil"},{"index":74,"identificacion":75,"barrio":"San Benito"},{"index":75,"identificacion":76,"barrio":"Buenos Aires"},{"index":76,"identificacion":77,"barrio":"Manrique"},{"index":77,"identificacion":78,"barrio":"San Benito"},{"index":78,"identificacion":79,"barrio":"Laureles"},{"index":79,"identificacion":80,"barrio":"San Benito"},{"index":80,"identificacion":81,"barrio":"San Benito"},{"index":81,"identificacion":82,"barrio":"Buenos Aires"},{"index":82,"identificacion":83,"barrio":"Laureles"},{"index":83,"identificacion":84,"barrio":"San Benito"},{"index":84,"identificacion":85,"barrio":"Manrique"},{"index":85,"identificacion":86,"barrio":"Manrique"},{"index":86,"identificacion":87,"barrio":"Guayaquil"},{"index":87,"identificacion":88,"barrio":"Laureles"},{"index":88,"identificacion":89,"barrio":"Laureles"},{"index":89,"identificacion":90,"barrio":"Guayaquil"},{"index":90,"identificacion":91,"barrio":"San Benito"},{"index":91,"identificacion":92,"barrio":"Laureles"},{"index":92,"identificacion":93,"barrio":"Manrique"},{"index":93,"identificacion":94,"barrio":"Manrique"},{"index":94,"identificacion":95,"barrio":"Buenos Aires"},{"index":95,"identificacion":96,"barrio":"Laureles"},{"index":96,"identificacion":97,"barrio":"San Benito"},{"index":97,"identificacion":98,"barrio":"Guayaquil"}]